bh
bytehold.py
setup.py
bytehold.egg-info/PKG-INFO
bytehold.egg-info/SOURCES.txt
bytehold.egg-info/dependency_links.txt
bytehold.egg-info/top_level.txt