Metadata-Version: 1.0
Name: bytehold
Version: 1.0
Summary: Simple backup tool, which helps not to repeat scripts.
Home-page: https://github.com/niwibe/bytehold
Author: Andrei Antoukh
Author-email: niwi@niwi.be
License: BSD
Platform: UNKNOWN
Classifier: Programming Language :: Python :: 3
Classifier: Programming Language :: Python :: 3.2
Classifier: Programming Language :: Python :: 3.3
Classifier: Development Status :: 4 - Beta
Classifier: Environment :: Console
Classifier: Intended Audience :: System Administrators
Classifier: License :: OSI Approved :: BSD License
Classifier: Operating System :: Unix
Classifier: Topic :: System :: Archiving :: Backup
Classifier: Topic :: System :: Systems Administration
